{
  "version": "7",
  "dialect": "postgresql",
  "entries": [
    {
      "idx": 0,
      "version": "7",
      "when": 1767467023541,
      "tag": "0000_wealthy_shiver_man",
      "breakpoints": true
    },
    {
      "idx": 1,
      "version": "7",
      "when": 1767475862871,
      "tag": "0001_sleepy_black_bird",
      "breakpoints": true
    },
    {
      "idx": 2,
      "version": "7",
      "when": 1767556730204,
      "tag": "0002_left_starhawk",
      "breakpoints": true
    },
    {
      "idx": 3,
      "version": "7",
      "when": 1767757942793,
      "tag": "0003_lethal_quicksilver",
      "breakpoints": true
    },
    {
      "idx": 4,
      "version": "7",
      "when": 1767928196726,
      "tag": "0004_medical_ogun",
      "breakpoints": true
    },
    {
      "idx": 5,
      "version": "7",
      "when": 1769550000000,
      "tag": "0005_friendly_party_size",
      "breakpoints": true
    }
  ]
}
